{
    "Willy": [
        {
            "location": "이집트 다합",
            "text": "당신은 세상 용감한 여행자입니다.\n끊임없이 도전하는 것을 즐기는군요!\n여행은 멀리, 도전은 많이!\n새로운 액티비티도 별로 고민하지 않고\n뛰어드는 당신!\n\n이집트 다합으로\n스쿠버다이빙 여행을 떠나는 건 어떨까요?",
            "color": "#e1ba86",
            "image": "eg_da",
            "icon": "eg_da"
        }, 
        {
            "location": "터키 이스탄불",
            "text": "당신은 여행도 도전적으로!\n쇼핑도 도전적으로 하는\n항상 도전적인 여행자입니다.\n기념품도 흔한 건 노노!\n그 나라에서 살 수 있는 것만\n구매하고 싶다구요?\n\n그렇다면 세상에서 가장 오래됐고\n가장 큰 터키 이스탄불의 그랜드바자르로 고고!",
            "color": "#8cc7d6",
            "image": "tur_i",
            "icon": "tur_i"
        }, 
        {
            "location": "이탈리아 나폴리",
            "text": "전투적으로 맛집을 찾아다니는 당신!\n새로운 음식도 두렵지 않아요!\n여행계의 맛있는 녀석들!\n새롭고 낯선 맛들을 찾아서\n구석구석 다니는 당신!\n더 이상 어떤 새로운 맛들이 있는지\n모르겠다구요?\n세상은 넓고, 맛있는 건 많다!\n\n이탈리아 나폴리의\n색다른 맛집을 찾아 떠나보세요!\n",
            "color": "#f6d9ac",
            "image": "it_na",
            "icon": "it_na"
        }, 
        {
            "location": "페루 쿠스코",
            "text": "'죽기 전에 내가 7대 불가사의를\n꼭 보아야만 하겠다!'라고\n생각하는 당신!\n어떤 여행지에서든 궁금한 것이 넘쳐요!\n세상에 너무 볼 것이 많나요?\n일단 이것부터 보고가시죠!\n\n잉카 문명의 발상지\n마추픽추 투어 어때요?",
            "color": "#9ccdb3",
            "image": "pe_ma",
            "icon": "pe_ma"
        }, 
        {
            "location": "요르단 와디럼",
            "text": "자연이 주는 풍경은 언제나 옳다!\n멋진 자연을 보기 위해서라면\n어디라도 갈 수 있다구요?\n얼마나 멀든, 얼마나 덥든\n그것은 상관이 없다구요?\n\n그렇다면 요르단의 붉은 사막을 보러\n와디럼으로 갈까요?",
            "color": "#d09289",
            "image": "yo_wa",
            "icon": "yo_wa"
        }, 
        {
            "location": "브라질 라우",
            "text": "시끌벅적 우당탕탕!\n새로운 사람들을 만나는 걸\n좋아하는 당신!\n새로운 사람들을 만나면\n기분이 조크든요!\n맥주 한잔을 손에 들고\n여행지에서 만난 친구들과\n즐거운 시간을 보내길 바란다구요?\n\n브라질 리우로 인생 친구 만들러 출발!\n",
            "color": "#c5c5c5",
            "image": "br_ra",
            "icon": "br_ra"
        }
    ],
    "Wigo": [
        {
            "location": "미국 로스엔젤레스",
            "text": "멀리 떠나서 재밌는 걸 해보자!\n너무 어렵고 무서운 건 싫다구요?\n서핑의 성지 로즈엔젤레스에\n가보는 것은 어때요?\n오래 머물면서\n로스엔젤레스의 서퍼가 되어보세요\n\n여행이 끝나면 이제 당신도 LA 서퍼!",
            "color": "#ea6369",
            "image": "us_san",
            "icon": "us_san"
        }, 
        {
            "location": "프랑스 파리",
            "text": "엘레강스한 쇼핑거리,\n노을색 조명이 주는 분위기를\n만끽하며 즐기는 쇼핑!\n당신은 고급스러운 욕망을\n숨기고 계시는군요!\n그렇다면 프랑스 파리\n샹젤리제로 떠나보아요!\n눈 돌아가는 가게들과\n거리의 분위기가\n당신의 두 손을 무겁게 할 거예요!\n\n자 파리 샤를드골행\n비행 티켓 준비 하셨나요?",
            "color": "#d4b79e",
            "image": "fr_pa",
            "icon": "fr_pa"
        }, 
        {
            "location": "독일 베를린",
            "text": "여행지에서 점심 맥주 한잔은\n진리라고 생각하는 당신!\n외국인 친구들도 사귀면\n금상첨화라구요?\n한손에는 맥주, 한손에는 소세지를 들고\n전세계의 여행자들과 어울리다보면\n여행이 짧게만 느껴질 것 같아요!\n\n마음껏 맥주를 들이부으러\n독일 베를린으로 떠나봐요!",
            "color": "#f7d1ab",
            "image": "gm_ber",
            "icon": "gm_ber"
        }, 
        {
            "location": "스페인 마드리드",
            "text": "사람들이 모여 사진 찍는 곳은\n그냥 못지나치는 당신!\n어떻게든 기다렸다가\n사진 한장은 찍고 나오시죠?\n세상 유명한 것들에 관심이 많으시다면!\n건축의 본좌 가우디의 건축물을 보러\n떠나시는 건 어떨까요?\n곳곳에 있는 가우디의 건축물들이\n당신의 여행을 특별하게\n만들어 줄 거예요!",
            "color": "#ddae6f",
            "image": "sp_ma",
            "icon": "sp_ma"
        }, 
        {
            "location": "미국 애리조나",
            "text": "그랜드캐니언은 못참지!\n미국 여행을 간다면 그랜드캐니언은\n절대 넘어갈 수 없는 당신!\n오프로드를 타고 그랜드캐니언을\n달리는 상상 한번쯤 해보셨죠?\n\n검증된 자연과 투어로\n미국 여행을 풍성하게 만들어보세요\n입이 떡 벌어질만한 자연의 자태가\n당신을 기다리고 있어요!\n",
            "color": "#87c3bc",
            "image": "us_a",
            "icon": "us_a"
        }, 
        {
            "location": "스페인 이비자",
            "text": "혹시 '언젠가 이비자 한번 가봐야지'\n생각하시나요?\n이비자 클럽 투어가\n버킷리스트에 있으시다구요?\n그렇다면 코로나가 끝난 후\n당장 달려가세요!\n\n광란의 스페인 이비자 파티가\n힘든 시기를 이겨낸 당신을\n더욱 즐겁게 해줄거예요!",
            "color": "#ddae6f",
            "image": "sp_i",
            "icon": "sp_ma"
        }
    ],
    "Tommy": [
        {
            "location": "말레이시아 코타키나발루",
            "text": "휴양지에서 할 만한 것을 찾는 당신!\n휴양지는 좋지만 지루한 것은 싫으신가요?\n그렇다면 검증된 바다 코타키나발루에서\n멋진 바다 속을 바라보는\n스노클링을 해보는 건 어떨까요?\n\n 코타키나발루의 바다 물고기들이\n당신에게 인사를 걸어올 거예요!\n",
            "color": "#8cc7d6",
            "image": "mal_ko",
            "icon": "mal_ko"
        }, 
        {
            "location": "말레이시아 쿠알라룸푸르",
            "text": "홍콩을 제친 쇼핑 명소 쿠알라룸푸르!\n혹시 알고 계셨나요?\n모르고 계셨다면\n지금 바로 여행을 준비해보세요!\n가깝지만 새삼 낯선 것을 좋아하는 당신!\n\n쿠알라룸푸르를 간다면\n괜히 쇼핑 명소가 아님을\n단번에 느낄 수 있을 거예요!",
            "color": "#8cc7d6",
            "image": "mal_ku",
            "icon": "mal_ko"
        }, 
        {
            "location": "말레이시아 페낭",
            "text": "같은 느낌의 미식 여행은 그만!\n조금은 더 색다른 미식투어가 필요한 당신!\n말레이시아 페낭으로 미식투어를 떠나보세요!\n한국에 전라도 밥상이 있다면\n말레이시아에는 페낭이 있다!\n\n맛있는 음식들의 향연을 페낭에서 만나보세요!",
            "color": "#8cc7d6",
            "image": "mal_pe",
            "icon": "mal_ko"
        }, 
        {
            "location": "캄보디아 앙코르",
            "text": "문화 예술 유적 답사를 좋아하는 당신!\n내성적이지만 개방적인 마인드를 가졌어요.\n휴양지에 왔더라도 한번 쯤\n고대 유적을 구경하는 것도 좋겠네요\n\n그렇다면 캄보디아의 대표적인 고대유적\n앙코르와트를 보러 앙코르로 떠나보아요!\n",
            "color": "#cfb5a3",
            "image": "kam_ang",
            "icon": "cam_ang"
        }, 
        {
            "location": "말레이시아 쿠알라룸푸르",
            "text": "가까운 곳에 놀라운\n자연풍경을 찾고 계신가요?\n너무 흔한 것은 싫지만,\n너무 먼 곳도 싫은 당신!\n조금 색다르게 쿠알라룸푸르 어때요?\n도심을 조금만 벗어나면\n놀라운 자연풍경이\n당신을 기다리고 있을거예요!\n\n친절한 사람들과 놀라운 자연풍경을 찾으러 \n쿠알라룸푸르로 출발!\n",
            "color": "#8cc7d6",
            "image": "mal_ku",
            "icon": "mal_ko"
        }, 
        {
            "location": "대만 타이페이",
            "text": "내적 흥이 상당한 당신!\n대놓고 춤을 추지는 못해도,\n속에서는 이미 댄스파티가 열렸어요!\n대만 특유희 야시장 거리를\n돌아다니며 흥을 돋구어보아요.\n\n언제든지 클럽파티에도 조인할 수 있는\n대만 타이페이 어떤가요?\n",
            "color": "#5dabb9",
            "image": "tw",
            "icon": "tw"
        }
    ],
    "Buddy": [
        {
            "location": "일본 삿포로",
            "text": "가깝고 익숙한 곳으로 향하는\n당신은 여행계의 집순이!\n여행은 가고싶고, 무서운 건 싫어!\n친숙한 곳에서 여유를 가지고\n여행하는 것을 좋아하는 당신!\n\n이웃나라 일본 삿포로 눈 축제에\n가보는 건 어떨까요?",
            "color": "#f7dce9",
            "image": "jp_sa",
            "icon": "jp_sa"
        }, 
        {
            "location": "싱가폴",
            "text": "익숙한 곳에서 쇼핑하는 것을\n좋아하는 당신!\n체계적인 쇼핑 계획을 세우시나요?\n어디서든 여행 중 쇼핑은 필수인 당신!\n\n보장된 쇼핑의 성지 싱가폴에서\n하루종일 쇼핑투어를 해봐요!",
            "color": "#e2bc9c",
            "image": "sing",
            "icon": "sg"
        }, 
        {
            "location": "일본 오사카",
            "text": "혹시 여행했던 곳에서의 맛집을\n잊지 못해서 다시 갈 계획을\n세우고 계시지는 않나요?\n여행을 맛으로 기억하는\n여행계의 절대미각!\n조금은 익숙하지만 특별한 맛을 찾아서!\n\n일본 오사카의 맛집을 찾아\n떠나보는 건 어때요?",
            "color": "#d6393e",
            "image": "jp_os",
            "icon": "jp_os"
        }, 
        {
            "location": "중국 베이징",
            "text": "크고 유명한 것부터 구경해야하는 당신!\n항상 어디선가 봤지만,\n실제로 보지 못한 만리장성을\n보러가는 것은 어때요?\n힘들고 어려운 여행은 싫다구요?\n걱정마세요!\n\n몸과 마음이 편안한\n만리장성 투어는 너무나 많답니다!",
            "color": "#eac8b0",
            "image": "ch_man",
            "icon": "ch_be"
        }, 
        {
            "location": "일본 시즈오카",
            "text": "한적한 온천에서\n자연을 바라보는 그런 여행\n기다리신다구요?\n그렇다면 후지산을 바라보며\n온천을 즐길 수 있는\n일본 시즈오카현으로 떠나보아요!\n가깝고 편하게 이동할 수 있고,\n맘 편히 휴식같은 여행을 할 수 있답니다.\n\n검증된 자연과 휴양!\n일본 시즈오카 여행을 준비해볼까요?",
            "color": "#d6393e",
            "image": "jp_hu",
            "icon": "jp_os"
        }, 
        {
            "location": "일본 도쿄",
            "text": "조용하고 안전한 여행과\n조금은 덜 북적거리는\n파티를 원하는 당신!\n치안이 좋고, 문화가 익숙한\n일본 도쿄로 떠나보세요!\n\n안전하고도 즐거운 저녁의\n도쿄를 만끽하다보면\n어느새 여행의 긴장도 다 풀리지 않을까요?\n",
            "color": "#d6393e",
            "image": "jp_to",
            "icon": "jp_os"
        }
    ]
}